pip_blame.py
pip_blame-0.2.4.dist-info/entry_points.txt
pip_blame-0.2.4.dist-info/WHEEL
pip_blame-0.2.4.dist-info/METADATA
pip_blame-0.2.4.dist-info/RECORD
