Metadata-Version: 2.1
Name: pip-blame
Version: 0.2.4
Summary: finds packages that prevent upgrading a transitive dependency
Author: banteg
Requires-Python: >=3.8
Requires-Dist: packaging >=24
Requires-Dist: requests >=2.31
Requires-Dist: rich >=13.7.1
Project-URL: Source, https://github.com/banteg/pip-blame
